pyhelperag/__init__.py
pyhelperag/dataframe_utils.py
pyhelperag/dict_utils.py
pyhelperag/file_utils.py
pyhelperag/math_utils.py
pyhelperag/memory_utils.py
pyhelperag/password_utils.py
pyhelperag/secure_utils.py
pyhelperag/system_utils.py
pyhelperag/time_utils.py
pyhelperag/zip_utils.py
pyhelperag-0.1.3.dist-info/METADATA
pyhelperag-0.1.3.dist-info/WHEEL
pyhelperag-0.1.3.dist-info/top_level.txt
pyhelperag-0.1.3.dist-info/RECORD
